sds011/__init__.py
sds011/sds011.py
sds011/examples/__init__.py
sds011/examples/sds011_console_test.py
sds011/utils/__init__.py
sds011/utils/databasehandler.py
sds011/utils/sockethandler.py
sds011-0.2.0.dist-info/LICENSE
sds011-0.2.0.dist-info/METADATA
sds011-0.2.0.dist-info/WHEEL
sds011-0.2.0.dist-info/top_level.txt
sds011-0.2.0.dist-info/RECORD
