Metadata-Version: 2.1
Name: sds011
Version: 0.2.0
Summary: A python 3 interface to a sds011 fine dust sensor
Home-page: https://github.com/menschel/sds011
Author: Patrick Menschel
Author-email: menschel.p@posteo.de
License: UNKNOWN
Keywords: fine dust sensor nova sds011
Platform: UNKNOWN
Classifier: Development Status :: 5 - Production/Stable
Classifier: Programming Language :: Python :: 3
Classifier: License :: OSI Approved :: GNU General Public License v3 or later (GPLv3+)
Classifier: Operating System :: OS Independent
Classifier: Intended Audience :: Science/Research
Classifier: Intended Audience :: Developers
Classifier: Topic :: Scientific/Engineering
Classifier: Topic :: Software Development :: Embedded Systems
Classifier: Topic :: Utilities
Requires-Python: >=3.6
Requires-Dist: pyserial
